{
  "assets" : {
    "B4764380454DE1B326AFE36B314D6D9B" : {
      "type" : "texture",
      "index" : 2,
      "assetRequest" : {
        "type" : "slide",
        "state" : "contents",
        "slide" : "none"
      },
      "url" : {
        "native" : "assets\/ABCEF1EB-E75A-4F49-BA92-670DA8B12102.pdf"
      },
      "width" : 292,
      "height" : 64
    },
    "B8AA3ECFA3CA30E98B20F355326225AA" : {
      "type" : "texture",
      "index" : 3,
      "assetRequest" : {
        "type" : "slide",
        "state" : "contents",
        "slide" : "none"
      },
      "url" : {
        "native" : "assets\/ABCEF1EB-E75A-4F49-BA92-670DA8B12102.pdf"
      },
      "width" : 725,
      "height" : 115
    },
    "A652FBF151FC9D26A0AD179EFB3719E4" : {
      "type" : "texture",
      "index" : 1,
      "assetRequest" : {
        "type" : "slide",
        "state" : "contents",
        "slide" : "none"
      },
      "url" : {
        "native" : "assets\/ABCEF1EB-E75A-4F49-BA92-670DA8B12102.pdf"
      },
      "width" : 219,
      "height" : 219
    },
    "CAAF099AB52B1AEF216B52210E1C8737" : {
      "type" : "texture",
      "index" : 0,
      "assetRequest" : {
        "type" : "slide",
        "state" : "contents",
        "slide" : "none"
      },
      "url" : {
        "native" : "assets\/ABCEF1EB-E75A-4F49-BA92-670DA8B12102.pdf"
      },
      "width" : 1024,
      "height" : 768
    },
    "7A4F397AC428108E564C4EDB511E945E" : {
      "type" : "texture",
      "index" : 5,
      "assetRequest" : {
        "type" : "slide",
        "state" : "contents",
        "slide" : "none"
      },
      "url" : {
        "native" : "assets\/ABCEF1EB-E75A-4F49-BA92-670DA8B12102.pdf"
      },
      "width" : 1024,
      "height" : 768
    },
    "480FDE6A0D39015FFBA56E03339CA00A" : {
      "type" : "texture",
      "index" : 4,
      "assetRequest" : {
        "type" : "slide",
        "state" : "contents",
        "slide" : "none"
      },
      "url" : {
        "native" : "assets\/ABCEF1EB-E75A-4F49-BA92-670DA8B12102.pdf"
      },
      "width" : 1024,
      "height" : 768
    }
  },
  "events" : [
    {
      "effects" : [
        {
          "beginTime" : 0,
          "baseLayer" : {
            "animations" : [

            ],
            "initialState" : {
              "affineTransform" : [
                1,
                0,
                0,
                1,
                0,
                0
              ],
              "masksToBounds" : false,
              "rotation" : 0,
              "scale" : 1,
              "position" : {
                "pointX" : 512,
                "pointY" : 384
              },
              "width" : 1024,
              "sublayerTransform" : [
                1,
                0,
                0,
                0,
                0,
                1,
                0,
                0,
                0,
                0,
                1,
                0,
                0,
                0,
                0,
                1
              ],
              "contentsRect" : {
                "y" : 0,
                "x" : 0,
                "width" : 1,
                "height" : 1
              },
              "opacity" : 1,
              "edgeAntialiasingMask" : 251658240,
              "height" : 768,
              "hidden" : false,
              "anchorPoint" : {
                "pointX" : 0.5,
                "pointY" : 0.5
              }
            },
            "objectID" : "0",
            "layers" : [
              {
                "animations" : [

                ],
                "initialState" : {
                  "affineTransform" : [
                    1,
                    0,
                    0,
                    1,
                    0,
                    0
                  ],
                  "masksToBounds" : false,
                  "rotation" : 0,
                  "scale" : 1,
                  "position" : {
                    "pointX" : 512,
                    "pointY" : 384
                  },
                  "width" : 1024,
                  "sublayerTransform" : [
                    1,
                    0,
                    0,
                    0,
                    0,
                    1,
                    0,
                    0,
                    0,
                    0,
                    1,
                    -0.00049229876906403734,
                    0,
                    0,
                    0,
                    1
                  ],
                  "contentsRect" : {
                    "y" : 0,
                    "x" : 0,
                    "width" : 1,
                    "height" : 1
                  },
                  "opacity" : 1,
                  "edgeAntialiasingMask" : 251658240,
                  "height" : 768,
                  "hidden" : false,
                  "anchorPoint" : {
                    "pointX" : 0.5,
                    "pointY" : 0.5
                  }
                },
                "layers" : [
                  {
                    "animations" : [

                    ],
                    "layers" : [

                    ],
                    "texturedRectangle" : {
                      "isBackgroundTexture" : false,
                      "singleTextureOpacity" : 1,
                      "textureType" : 0,
                      "textBaseline" : 0,
                      "textXHeight" : 0,
                      "isVerticalText" : false
                    },
                    "initialState" : {
                      "affineTransform" : [
                        1,
                        0,
                        0,
                        1,
                        0,
                        0
                      ],
                      "masksToBounds" : false,
                      "rotation" : 0,
                      "scale" : 1,
                      "position" : {
                        "pointX" : 512,
                        "pointY" : 384
                      },
                      "width" : 1024,
                      "sublayerTransform" : [
                        1,
                        0,
                        0,
                        0,
                        0,
                        1,
                        0,
                        0,
                        0,
                        0,
                        1,
                        0,
                        0,
                        0,
                        0,
                        1
                      ],
                      "contentsRect" : {
                        "y" : 0,
                        "x" : 0,
                        "width" : 1,
                        "height" : 1
                      },
                      "opacity" : 1,
                      "edgeAntialiasingMask" : 0,
                      "height" : 768,
                      "hidden" : false,
                      "anchorPoint" : {
                        "pointX" : 0.5,
                        "pointY" : 0.5
                      }
                    },
                    "texture" : "480FDE6A0D39015FFBA56E03339CA00A"
                  },
                  {
                    "animations" : [
                      {
                        "timeOffset" : 0,
                        "from" : {
                          "scalar" : false
                        },
                        "beginTime" : 0,
                        "repeatCount" : 0,
                        "fillMode" : "both",
                        "property" : "hidden",
                        "autoreverses" : false,
                        "duration" : 0.01,
                        "to" : {
                          "scalar" : true
                        }
                      }
                    ],
                    "layers" : [

                    ],
                    "texturedRectangle" : {
                      "isBackgroundTexture" : false,
                      "singleTextureOpacity" : 1,
                      "textureType" : 0,
                      "textBaseline" : 0,
                      "textXHeight" : 0,
                      "isVerticalText" : false
                    },
                    "initialState" : {
                      "affineTransform" : [
                        1,
                        0,
                        0,
                        1,
                        0,
                        0
                      ],
                      "masksToBounds" : false,
                      "rotation" : 0,
                      "scale" : 1,
                      "position" : {
                        "pointX" : 512,
                        "pointY" : 384
                      },
                      "width" : 1024,
                      "sublayerTransform" : [
                        1,
                        0,
                        0,
                        0,
                        0,
                        1,
                        0,
                        0,
                        0,
                        0,
                        1,
                        0,
                        0,
                        0,
                        0,
                        1
                      ],
                      "contentsRect" : {
                        "y" : 0,
                        "x" : 0,
                        "width" : 1,
                        "height" : 1
                      },
                      "opacity" : 1,
                      "edgeAntialiasingMask" : 0,
                      "height" : 768,
                      "hidden" : false,
                      "anchorPoint" : {
                        "pointX" : 0.5,
                        "pointY" : 0.5
                      }
                    },
                    "texture" : "7A4F397AC428108E564C4EDB511E945E"
                  }
                ]
              }
            ]
          },
          "effects" : [

          ],
          "duration" : 0.01,
          "type" : "transition",
          "name" : "none",
          "objectID" : "0"
        }
      ],
      "automaticPlay" : false,
      "hyperlinks" : [

      ],
      "accessibility" : [
        {
          "text" : "XojoLogo.pdf",
          "targetRectangle" : {
            "y" : 15,
            "x" : 788,
            "width" : 216.00001525878906,
            "height" : 216.00001525878906
          }
        },
        {
          "text" : "TaskList",
          "targetRectangle" : {
            "y" : 73,
            "x" : 66,
            "width" : 282.59999999999997,
            "height" : 85.9114990234375
          }
        },
        {
          "text" : "Collection of TaskItems",
          "targetRectangle" : {
            "y" : 222,
            "x" : 100.99999952316284,
            "width" : 356.72399999999993,
            "height" : 66.95574951171875
          }
        },
        {
          "text" : "Knows how add, complete and delete tasks",
          "targetRectangle" : {
            "y" : 290,
            "x" : 100.99999952316284,
            "width" : 681.4799999999999,
            "height" : 42.95574951171875
          }
        }
      ],
      "baseLayer" : {
        "animations" : [

        ],
        "initialState" : {
          "affineTransform" : [
            1,
            0,
            0,
            1,
            0,
            0
          ],
          "masksToBounds" : false,
          "rotation" : 0,
          "scale" : 1,
          "position" : {
            "pointX" : 512,
            "pointY" : 384
          },
          "width" : 1024,
          "sublayerTransform" : [
            1,
            0,
            0,
            0,
            0,
            1,
            0,
            0,
            0,
            0,
            1,
            0,
            0,
            0,
            0,
            1
          ],
          "contentsRect" : {
            "y" : 0,
            "x" : 0,
            "width" : 1,
            "height" : 1
          },
          "opacity" : 1,
          "edgeAntialiasingMask" : 251658240,
          "height" : 768,
          "hidden" : false,
          "anchorPoint" : {
            "pointX" : 0.5,
            "pointY" : 0.5
          }
        },
        "objectID" : "0",
        "layers" : [
          {
            "animations" : [

            ],
            "initialState" : {
              "affineTransform" : [
                1,
                0,
                0,
                1,
                0,
                0
              ],
              "masksToBounds" : false,
              "rotation" : 0,
              "scale" : 1,
              "position" : {
                "pointX" : 512,
                "pointY" : 384
              },
              "width" : 1024,
              "sublayerTransform" : [
                1,
                0,
                0,
                0,
                0,
                1,
                0,
                0,
                0,
                0,
                1,
                0,
                0,
                0,
                0,
                1
              ],
              "contentsRect" : {
                "y" : 0,
                "x" : 0,
                "width" : 1,
                "height" : 1
              },
              "opacity" : 1,
              "edgeAntialiasingMask" : 251658240,
              "height" : 768,
              "hidden" : false,
              "anchorPoint" : {
                "pointX" : 0.5,
                "pointY" : 0.5
              }
            },
            "layers" : [
              {
                "animations" : [

                ],
                "initialState" : {
                  "affineTransform" : [
                    1,
                    0,
                    0,
                    1,
                    0,
                    0
                  ],
                  "masksToBounds" : false,
                  "rotation" : 0,
                  "scale" : 1,
                  "position" : {
                    "pointX" : 512,
                    "pointY" : 384
                  },
                  "width" : 1024,
                  "sublayerTransform" : [
                    1,
                    0,
                    0,
                    0,
                    0,
                    1,
                    0,
                    0,
                    0,
                    0,
                    1,
                    0,
                    0,
                    0,
                    0,
                    1
                  ],
                  "contentsRect" : {
                    "y" : 0,
                    "x" : 0,
                    "width" : 1,
                    "height" : 1
                  },
                  "opacity" : 1,
                  "edgeAntialiasingMask" : 251658240,
                  "height" : 768,
                  "hidden" : false,
                  "anchorPoint" : {
                    "pointX" : 0.5,
                    "pointY" : 0.5
                  }
                },
                "layers" : [
                  {
                    "animations" : [

                    ],
                    "layers" : [

                    ],
                    "texturedRectangle" : {
                      "isBackgroundTexture" : true,
                      "singleTextureOpacity" : 1,
                      "textureType" : 1,
                      "textBaseline" : 0,
                      "textXHeight" : 0,
                      "isVerticalText" : false
                    },
                    "initialState" : {
                      "affineTransform" : [
                        1,
                        0,
                        0,
                        1,
                        0,
                        0
                      ],
                      "masksToBounds" : false,
                      "rotation" : 0,
                      "scale" : 1,
                      "position" : {
                        "pointX" : 512,
                        "pointY" : 384
                      },
                      "width" : 1024,
                      "sublayerTransform" : [
                        1,
                        0,
                        0,
                        0,
                        0,
                        1,
                        0,
                        0,
                        0,
                        0,
                        1,
                        0,
                        0,
                        0,
                        0,
                        1
                      ],
                      "contentsRect" : {
                        "y" : 0,
                        "x" : 0,
                        "width" : 1,
                        "height" : 1
                      },
                      "opacity" : 1,
                      "edgeAntialiasingMask" : 0,
                      "height" : 768,
                      "hidden" : false,
                      "anchorPoint" : {
                        "pointX" : 0.5,
                        "pointY" : 0.5
                      }
                    },
                    "texture" : "CAAF099AB52B1AEF216B52210E1C8737"
                  }
                ]
              }
            ]
          },
          {
            "animations" : [

            ],
            "initialState" : {
              "affineTransform" : [
                1,
                0,
                0,
                1,
                0,
                0
              ],
              "masksToBounds" : false,
              "rotation" : 0,
              "scale" : 1,
              "position" : {
                "pointX" : 512,
                "pointY" : 384
              },
              "width" : 1024,
              "sublayerTransform" : [
                1,
                0,
                0,
                0,
                0,
                1,
                0,
                0,
                0,
                0,
                1,
                0,
                0,
                0,
                0,
                1
              ],
              "contentsRect" : {
                "y" : 0,
                "x" : 0,
                "width" : 1,
                "height" : 1
              },
              "opacity" : 1,
              "edgeAntialiasingMask" : 251658240,
              "height" : 768,
              "hidden" : false,
              "anchorPoint" : {
                "pointX" : 0.5,
                "pointY" : 0.5
              }
            },
            "layers" : [
              {
                "animations" : [

                ],
                "initialState" : {
                  "affineTransform" : [
                    1,
                    0,
                    0,
                    1,
                    0,
                    0
                  ],
                  "masksToBounds" : false,
                  "rotation" : 0,
                  "scale" : 1,
                  "position" : {
                    "pointX" : 897.5,
                    "pointY" : 124.5
                  },
                  "width" : 219,
                  "sublayerTransform" : [
                    1,
                    0,
                    0,
                    0,
                    0,
                    1,
                    0,
                    0,
                    0,
                    0,
                    1,
                    0,
                    0,
                    0,
                    0,
                    1
                  ],
                  "contentsRect" : {
                    "y" : 0,
                    "x" : 0,
                    "width" : 1,
                    "height" : 1
                  },
                  "opacity" : 0.25,
                  "edgeAntialiasingMask" : 251658240,
                  "height" : 219,
                  "hidden" : false,
                  "anchorPoint" : {
                    "pointX" : 0.5,
                    "pointY" : 0.5
                  }
                },
                "layers" : [
                  {
                    "animations" : [

                    ],
                    "layers" : [

                    ],
                    "texturedRectangle" : {
                      "isBackgroundTexture" : true,
                      "singleTextureOpacity" : 0.25,
                      "textureType" : 5,
                      "textBaseline" : 0,
                      "textXHeight" : 0,
                      "isVerticalText" : false
                    },
                    "initialState" : {
                      "affineTransform" : [
                        1,
                        0,
                        0,
                        1,
                        0,
                        0
                      ],
                      "masksToBounds" : false,
                      "rotation" : 0,
                      "scale" : 1,
                      "position" : {
                        "pointX" : 108.5,
                        "pointY" : 108.5
                      },
                      "width" : 219,
                      "sublayerTransform" : [
                        1,
                        0,
                        0,
                        0,
                        0,
                        1,
                        0,
                        0,
                        0,
                        0,
                        1,
                        0,
                        0,
                        0,
                        0,
                        1
                      ],
                      "contentsRect" : {
                        "y" : 0,
                        "x" : 0,
                        "width" : 1,
                        "height" : 1
                      },
                      "opacity" : 1,
                      "edgeAntialiasingMask" : 0,
                      "height" : 219,
                      "hidden" : false,
                      "anchorPoint" : {
                        "pointX" : 0.5,
                        "pointY" : 0.5
                      }
                    },
                    "texture" : "A652FBF151FC9D26A0AD179EFB3719E4"
                  }
                ]
              }
            ]
          },
          {
            "animations" : [

            ],
            "initialState" : {
              "affineTransform" : [
                1,
                0,
                0,
                1,
                0,
                0
              ],
              "masksToBounds" : false,
              "rotation" : 0,
              "scale" : 1,
              "position" : {
                "pointX" : 512,
                "pointY" : 384
              },
              "width" : 1024,
              "sublayerTransform" : [
                1,
                0,
                0,
                0,
                0,
                1,
                0,
                0,
                0,
                0,
                1,
                0,
                0,
                0,
                0,
                1
              ],
              "contentsRect" : {
                "y" : 0,
                "x" : 0,
                "width" : 1,
                "height" : 1
              },
              "opacity" : 1,
              "edgeAntialiasingMask" : 251658240,
              "height" : 768,
              "hidden" : false,
              "anchorPoint" : {
                "pointX" : 0.5,
                "pointY" : 0.5
              }
            },
            "layers" : [
              {
                "animations" : [

                ],
                "initialState" : {
                  "affineTransform" : [
                    1,
                    0,
                    0,
                    1,
                    0,
                    0
                  ],
                  "masksToBounds" : false,
                  "rotation" : 0,
                  "scale" : 1,
                  "position" : {
                    "pointX" : 208,
                    "pointY" : 52
                  },
                  "width" : 292,
                  "sublayerTransform" : [
                    1,
                    0,
                    0,
                    0,
                    0,
                    1,
                    0,
                    0,
                    0,
                    0,
                    1,
                    0,
                    0,
                    0,
                    0,
                    1
                  ],
                  "contentsRect" : {
                    "y" : 0,
                    "x" : 0,
                    "width" : 1,
                    "height" : 1
                  },
                  "opacity" : 1,
                  "edgeAntialiasingMask" : 251658240,
                  "height" : 64,
                  "hidden" : false,
                  "anchorPoint" : {
                    "pointX" : 0.5,
                    "pointY" : 0.5
                  }
                },
                "layers" : [
                  {
                    "animations" : [

                    ],
                    "layers" : [

                    ],
                    "texturedRectangle" : {
                      "singleTextureOpacity" : 1,
                      "textXHeight" : 0.58162499999999995,
                      "textBaseline" : 0.84824752807617188,
                      "isBackgroundTexture" : true,
                      "isVerticalText" : false,
                      "textColor" : [
                        0.9999966025352478,
                        0.99999994039535522,
                        0.99999994039535522,
                        1
                      ],
                      "textureType" : 6
                    },
                    "initialState" : {
                      "affineTransform" : [
                        1,
                        0,
                        0,
                        1,
                        0,
                        0
                      ],
                      "masksToBounds" : false,
                      "rotation" : 0,
                      "scale" : 1,
                      "position" : {
                        "pointX" : 145,
                        "pointY" : 101
                      },
                      "width" : 292,
                      "sublayerTransform" : [
                        1,
                        0,
                        0,
                        0,
                        0,
                        1,
                        0,
                        0,
                        0,
                        0,
                        1,
                        0,
                        0,
                        0,
                        0,
                        1
                      ],
                      "contentsRect" : {
                        "y" : 0,
                        "x" : 0,
                        "width" : 1,
                        "height" : 1
                      },
                      "opacity" : 1,
                      "edgeAntialiasingMask" : 0,
                      "height" : 64,
                      "hidden" : false,
                      "anchorPoint" : {
                        "pointX" : 0.5,
                        "pointY" : 0.5
                      }
                    },
                    "texture" : "B4764380454DE1B326AFE36B314D6D9B"
                  }
                ]
              }
            ]
          },
          {
            "animations" : [

            ],
            "initialState" : {
              "affineTransform" : [
                1,
                0,
                0,
                1,
                0,
                0
              ],
              "masksToBounds" : false,
              "rotation" : 0,
              "scale" : 1,
              "position" : {
                "pointX" : 512,
                "pointY" : 384
              },
              "width" : 1024,
              "sublayerTransform" : [
                1,
                0,
                0,
                0,
                0,
                1,
                0,
                0,
                0,
                0,
                1,
                0,
                0,
                0,
                0,
                1
              ],
              "contentsRect" : {
                "y" : 0,
                "x" : 0,
                "width" : 1,
                "height" : 1
              },
              "opacity" : 1,
              "edgeAntialiasingMask" : 251658240,
              "height" : 768,
              "hidden" : false,
              "anchorPoint" : {
                "pointX" : 0.5,
                "pointY" : 0.5
              }
            },
            "layers" : [
              {
                "animations" : [

                ],
                "initialState" : {
                  "affineTransform" : [
                    1,
                    0,
                    0,
                    1,
                    0,
                    0
                  ],
                  "masksToBounds" : false,
                  "rotation" : 0,
                  "scale" : 1,
                  "position" : {
                    "pointX" : 424.5,
                    "pointY" : 275.5
                  },
                  "width" : 725,
                  "sublayerTransform" : [
                    1,
                    0,
                    0,
                    0,
                    0,
                    1,
                    0,
                    0,
                    0,
                    0,
                    1,
                    0,
                    0,
                    0,
                    0,
                    1
                  ],
                  "contentsRect" : {
                    "y" : 0,
                    "x" : 0,
                    "width" : 1,
                    "height" : 1
                  },
                  "opacity" : 1,
                  "edgeAntialiasingMask" : 251658240,
                  "height" : 115,
                  "hidden" : false,
                  "anchorPoint" : {
                    "pointX" : 0.5,
                    "pointY" : 0.5
                  }
                },
                "layers" : [
                  {
                    "animations" : [

                    ],
                    "layers" : [

                    ],
                    "texturedRectangle" : {
                      "singleTextureOpacity" : 1,
                      "textXHeight" : 0.16372173913043478,
                      "textBaseline" : 0.86337253736413044,
                      "isBackgroundTexture" : true,
                      "isVerticalText" : false,
                      "textColor" : [
                        0.9999966025352478,
                        0.99999994039535522,
                        0.99999994039535522,
                        1
                      ],
                      "textureType" : 6
                    },
                    "initialState" : {
                      "affineTransform" : [
                        1,
                        0,
                        0,
                        1,
                        0,
                        0
                      ],
                      "masksToBounds" : false,
                      "rotation" : 0,
                      "scale" : 1,
                      "position" : {
                        "pointX" : 362.5,
                        "pointY" : 65.5
                      },
                      "width" : 725,
                      "sublayerTransform" : [
                        1,
                        0,
                        0,
                        0,
                        0,
                        1,
                        0,
                        0,
                        0,
                        0,
                        1,
                        0,
                        0,
                        0,
                        0,
                        1
                      ],
                      "contentsRect" : {
                        "y" : 0,
                        "x" : 0,
                        "width" : 1,
                        "height" : 1
                      },
                      "opacity" : 1,
                      "edgeAntialiasingMask" : 0,
                      "height" : 115,
                      "hidden" : false,
                      "anchorPoint" : {
                        "pointX" : 0.5,
                        "pointY" : 0.5
                      }
                    },
                    "texture" : "B8AA3ECFA3CA30E98B20F355326225AA"
                  }
                ]
              }
            ]
          }
        ]
      }
    }
  ]
}